discordaio/__init__.py
discordaio/activity.py
discordaio/base.py
discordaio/channel.py
discordaio/client.py
discordaio/constants.py
discordaio/emoji.py
discordaio/enums.py
discordaio/exceptions.py
discordaio/guild.py
discordaio/http.py
discordaio/invite.py
discordaio/permissions.py
discordaio/role.py
discordaio/user.py
discordaio/version.py
discordaio/voice.py
discordaio/webhook.py
discordaio/websocket.py
discord.aio-0.3.1.dist-info/LICENSE.txt
discord.aio-0.3.1.dist-info/METADATA
discord.aio-0.3.1.dist-info/WHEEL
discord.aio-0.3.1.dist-info/top_level.txt
discord.aio-0.3.1.dist-info/RECORD
