Metadata-Version: 2.1
Name: discord.aio
Version: 0.3.1
Summary: discord.aio is an asynchronous Discord API wrapper for asyncio and python
Home-page: https://github.com/edg-l/discord.aio
Author: Edgar
Author-email: git@edgarluque.com
License: MIT
Keywords: discord,wrapper,api,bot,asyncio
Platform: UNKNOWN
Classifier: Development Status :: 2 - Pre-Alpha
Classifier: Intended Audience :: Developers
Classifier: Natural Language :: English
Classifier: Operating System :: OS Independent
Classifier: Topic :: Utilities
Classifier: Topic :: Software Development :: Libraries
Classifier: Topic :: Software Development :: Libraries :: Python Modules
Classifier: License :: OSI Approved :: MIT License
Classifier: Programming Language :: Python :: 3.6
Requires-Python: >=3.6
Requires-Dist: aiohttp
